paneleventstudy/__init__.py
paneleventstudy/__main__.py
paneleventstudy/dataprep.py
paneleventstudy/eventstudyplot.py
paneleventstudy/interactionweighted_eventstudy.py
paneleventstudy/naivetwfe_eventstudy.py
paneleventstudy/timeseries_eventstudy.py
paneleventstudy-0.0.7.dist-info/LICENSE
paneleventstudy-0.0.7.dist-info/METADATA
paneleventstudy-0.0.7.dist-info/WHEEL
paneleventstudy-0.0.7.dist-info/entry_points.txt
paneleventstudy-0.0.7.dist-info/top_level.txt
paneleventstudy-0.0.7.dist-info/RECORD
