Metadata-Version: 2.2
Name: paneleventstudy
Version: 0.0.7
Summary: This module implements the panel (and single entity) event study models, covering the naive two-way fixed effects implementation, and the interaction-weighted implementation from Sun and Abraham (2021).
Author-email: Jing Lian Suah <jlsuah@hkma.gov.hk>
License: MIT License
Project-URL: PyPI, https://pypi.org/project/paneleventstudy/
Project-URL: GitHub, https://github.com/suahjl/paneleventstudy/
Keywords: Econometrics,Event Study,Panel Data,Time Series
Classifier: License :: OSI Approved :: MIT License
Classifier: Programming Language :: Python
Classifier: Programming Language :: Python :: 3
Requires-Python: >=3.9
License-File: LICENSE
Requires-Dist: pandas>=1.4.3
Requires-Dist: numpy>=1.23.0
Requires-Dist: linearmodels>=4.27
Requires-Dist: plotly>=5.9.0
Requires-Dist: statsmodels>=0.13.2
Requires-Dist: sympy>=1.10.1
Provides-Extra: dev
